odoo/addons/sale_report_viewer/__init__.py
odoo/addons/sale_report_viewer/__manifest__.py
odoo/addons/sale_report_viewer/static/description/icon.png
odoo/addons/sale_report_viewer/views/sale.xml
odoo12_addon_sale_report_viewer-12.0.1.0.0.99.dev2.dist-info/METADATA
odoo12_addon_sale_report_viewer-12.0.1.0.0.99.dev2.dist-info/WHEEL
odoo12_addon_sale_report_viewer-12.0.1.0.0.99.dev2.dist-info/top_level.txt
odoo12_addon_sale_report_viewer-12.0.1.0.0.99.dev2.dist-info/RECORD
